cramer/__init__.py
cramer/cramer.py
cramer-0.0.0.dist-info/METADATA
cramer-0.0.0.dist-info/WHEEL
cramer-0.0.0.dist-info/top_level.txt
cramer-0.0.0.dist-info/RECORD
