Metadata-Version: 2.1
Name: cramer
Version: 0.0.0
Summary: This is a library designed to solve systems of linear equations using the cramer solution method.
Home-page: https://github.com/TeengardenB/cramer
Author: Teengarden B
Author-email: teengardenb@gmail.com
License: MIT
Platform: UNKNOWN
Requires-Dist: numpy
